{"kind":"goodUserData","message":"The user data was successfully retrieved.","data":{"name":"GrapeFruitMerchant","ctftimeId":null,"division":"open","score":1876,"globalPlace":199,"divisionPlace":199,"solves":[{"category":"misc","name":"Feedback Survey","points":200,"solves":183,"id":"feedback","createdAt":1719774616155},{"category":"osint","name":"Chunky Boi","points":319,"solves":225,"id":"plane","createdAt":1719693455380},{"category":"osint","name":"The Weakest Link","points":393,"solves":149,"id":"the-weakest-link","createdAt":1719689070721},{"category":"crypto","name":"Determined","points":322,"solves":222,"id":"determined","createdAt":1719637877217},{"category":"crypto","name":"Without a Trace","points":246,"solves":298,"id":"without-a-trace","createdAt":1719635240929},{"category":"crypto","name":"X Marked the Spot","points":93,"solves":531,"id":"marked","createdAt":1719631899657},{"category":"osint","name":"Night","points":121,"solves":466,"id":"city","createdAt":1719630627304},{"category":"osint","name":"An Unlikely Partnership","points":100,"solves":511,"id":"an-unlikely-partnership","createdAt":1719626564239},{"category":"osint","name":"Hip With the Youth","points":81,"solves":567,"id":"hip-with-the-youth","createdAt":1719624899171},{"category":"misc","name":"Sanity Check","points":1,"solves":757,"id":"sanity-check","createdAt":1719620157946}]}}