{"kind":"goodUserData","message":"The user data was successfully retrieved.","data":{"name":"ri5e","ctftimeId":null,"division":"open","score":1043,"globalPlace":311,"divisionPlace":311,"solves":[{"category":"misc","name":"Sanity Check","points":1,"solves":757,"id":"sanity-check","createdAt":1719731412828},{"category":"crypto","name":"Determined","points":322,"solves":222,"id":"determined","createdAt":1719731249845},{"category":"rev","name":"Summarize","points":381,"solves":161,"id":"summarize","createdAt":1719711294827},{"category":"crypto","name":"Without a Trace","points":246,"solves":298,"id":"without-a-trace","createdAt":1719707717337},{"category":"crypto","name":"X Marked the Spot","points":93,"solves":531,"id":"marked","createdAt":1719701858009}]}}